DockerLibrary.py
Utils.py
robotframework_dockerlibrary-1.0.0.data/data/images/alpine/Dockerfile
robotframework_dockerlibrary-1.0.0.data/data/images/centos/Dockerfile
robotframework_dockerlibrary-1.0.0.data/data/images/ubuntu/Dockerfile
robotframework_dockerlibrary-1.0.0.dist-info/LICENSE.txt
robotframework_dockerlibrary-1.0.0.dist-info/METADATA
robotframework_dockerlibrary-1.0.0.dist-info/WHEEL
robotframework_dockerlibrary-1.0.0.dist-info/top_level.txt
robotframework_dockerlibrary-1.0.0.dist-info/RECORD
