Metadata-Version: 2.1
Name: robotframework-dockerlibrary
Version: 1.0.0
Summary: A Robot Framework Docker Library
Home-page: UNKNOWN
Author: Oliver Uhlar
Author-email: oliverkolombo@gmail.com
License: Apache License 2.0
Keywords: testing testautomation robotframework docker dind containerization
Platform: UNKNOWN
Classifier: Development Status :: 5 - Production/Stable
Classifier: Intended Audience :: Developers
Classifier: Topic :: Software Development :: Testing
Classifier: License :: OSI Approved :: Apache Software License
Classifier: Programming Language :: Python :: 3.8
Classifier: Framework :: Robot Framework :: Library
Requires-Dist: packaging
Requires-Dist: robotframework (==4.1.2)
